kv_cache/__init__.py
kv_cache/main.py
kv_cache-0.3.3.dist-info/METADATA
kv_cache-0.3.3.dist-info/WHEEL
kv_cache-0.3.3.dist-info/licenses/LICENSE
kv_cache-0.3.3.dist-info/RECORD
