Metadata-Version: 2.4
Name: kv-cache
Version: 0.3.3
Summary: A fast key-value store using SQLite for CLI tools
Project-URL: Homepage, https://github.com/yourusername/fast-kv
Project-URL: Repository, https://github.com/yourusername/fast-kv.git
Project-URL: Documentation, https://github.com/yourusername/fast-kv#readme
Project-URL: Bug Tracker, https://github.com/yourusername/fast-kv/issues
Author-email: Your Name <your.email@example.com>
License-Expression: MIT
License-File: LICENSE
Keywords: cache,cli,key-value,sqlite
Classifier: Development Status :: 4 - Beta
Classifier: Intended Audience :: Developers
Classifier: License :: OSI Approved :: MIT License
Classifier: Programming Language :: Python :: 3
Classifier: Programming Language :: Python :: 3.7
Classifier: Programming Language :: Python :: 3.8
Classifier: Programming Language :: Python :: 3.9
Classifier: Programming Language :: Python :: 3.10
Classifier: Programming Language :: Python :: 3.11
Classifier: Topic :: Software Development :: Libraries :: Python Modules
Requires-Python: >=3.7
Provides-Extra: dev
Requires-Dist: black>=22.0; extra == 'dev'
Requires-Dist: isort>=5.0; extra == 'dev'
Requires-Dist: mypy>=0.981; extra == 'dev'
Requires-Dist: pytest-asyncio>=0.25.0; extra == 'dev'
Requires-Dist: pytest-cov>=3.0; extra == 'dev'
Requires-Dist: pytest>=7.0; extra == 'dev'
